{
  "display_name": "English",
  "label.language": "Language",
  "label.language.tooltip": "Change your target language in the editor.",
  "label.setting": "Settings",
  "label.setting.tooltip": "Settings",
  "label.setting.enable_by_default": "Enable by Default",
  "label.setting.enable_by_default.tooltip": "Miso shadow will turn on by default",
  "label.setting.use_write_defaults": "Use Write Defaults",
  "label.setting.use_write_defaults.tooltip": "Use write defaults in animation controller",
  "label.setting.savable_shadow_strength": "Savable Shadow Strength",
  "label.setting.savable_shadow_strength.tooltip": "Shadow strength parameter will be saved by default",
  "label.setting.savable_shadow_angle": "Savable Shadow Angle",
  "label.setting.savable_shadow_angle.tooltip": "Shadow angle parameter will be saved by default",
  "label.dev": "Devs settings",
  "label.dev.tooltip": "Devs settings",
  "label.dev.menu_root": "Menu Root",
  "label.dev.menu_root.tooltip": "The menu root of installer",
  "label.ignore": "This object will be ignore when 'Miso Shadow NDMF' is installing",
  "menu.shadow_strength": "Shadow Strength",
  "menu.shadow_angle": "Shadow Angle",
  "menu.toggle_angle": "Toggle Angle",
  "menu.reset": "Reset"
}